Alpyne/__init__.py
Alpyne/client.py
Alpyne/containers.py
Alpyne/functions.py
Alpyne-0.0.1.dist-info/METADATA
Alpyne-0.0.1.dist-info/WHEEL
Alpyne-0.0.1.dist-info/top_level.txt
Alpyne-0.0.1.dist-info/RECORD
