Metadata-Version: 2.1
Name: Alpyne
Version: 0.0.1
Summary: A grid computing framework in python
Home-page: https://github.com/mohitudupa/Alpyne.git
Author: UNKNOWN
Author-email: UNKNOWN
License: UNKNOWN
Platform: UNKNOWN
Requires-Dist: requests
Requires-Dist: pymongo
